CHANGELOG.md
LICENSE
MANIFEST.in
README.md
setup.cfg
setup.py
pip_services3_mysql/__init__.py
pip_services3_mysql.egg-info/PKG-INFO
pip_services3_mysql.egg-info/SOURCES.txt
pip_services3_mysql.egg-info/dependency_links.txt
pip_services3_mysql.egg-info/requires.txt
pip_services3_mysql.egg-info/top_level.txt
pip_services3_mysql.egg-info/zip-safe
pip_services3_mysql/build/DefaultMySqlFactory.py
pip_services3_mysql/build/__init__.py
pip_services3_mysql/connect/MySqlConnection.py
pip_services3_mysql/connect/MySqlConnectionResolver.py
pip_services3_mysql/connect/__init__.py
pip_services3_mysql/persistence/IdentifiableJsonMySqlPersistence.py
pip_services3_mysql/persistence/IdentifiableMySqlPersistence.py
pip_services3_mysql/persistence/MySqlPersistence.py
pip_services3_mysql/persistence/__init__.py
test/connect/__init__.py
test/connect/test_MySqlConnectionResolver.py
test/fixtures/Dummy.py
test/fixtures/Dummy2.py
test/fixtures/Dummy2PersistenceFixture.py
test/fixtures/DummyPersistenceFixture.py
test/fixtures/IDummy2Persistence.py
test/fixtures/IDummyPersistence.py
test/fixtures/__init__.py
test/persistence/Dummy2MySqlPersistence.py
test/persistence/DummyJsonMySqlPersistence.py
test/persistence/DummyMySqlPersistence.py
test/persistence/__init__.py
test/persistence/test_Dummy2MySqlPersistence.py
test/persistence/test_DummyJsonMySqlPersistence.py
test/persistence/test_DummyMySqlConnection.py
test/persistence/test_DummyMySqlPersistence.py
test/persistence/test_MySqlConnection.py